TestQuizzer/__init__.py
TestQuizzer/__main__.py
TestQuizzer/db_quizzes/english-speaking-small-talk_quiz.json
TestQuizzer/db_quizzes/english-speaking-weather-vocabulary-quiz.json
TestQuizzer/db_quizzes/english-vocabulary-animal-terms-quiz.json
TestQuizzer/db_quizzes/english-vocabulary-collocations-quiz-time.json
TestQuizzer/db_quizzes/english-vocabulary-computer-quiz.json
TestQuizzer/db_quizzes/english-vocabulary-criminals-quiz.json
TestQuizzer/db_quizzes/english-vocabulary-family-quiz.json
TestQuizzer/db_quizzes/english-vocabulary-festivals-christmas-quiz.json
TestQuizzer/db_quizzes/english-vocabulary-nsew-quiz.json
TestQuizzer/db_quizzes/english-vocabulary-numbers-quiz.json
TestQuizzer/db_quizzes/english-vocabulary-time-quiz.json
TestQuizzer/db_quizzes/english-vocabulary-weather-vocabulary-quiz.json
TestQuizzer/db_quizzes/english-vocabulary-world-countries-nationality-quiz.json
TestQuizzer/db_results/.gitkeep
TestQuizzer/quizuiflowcontrol/__init__.py
TestQuizzer/quizuiflowcontrol/main_menu.py
TestQuizzer/quizuiflowcontrol/quizmanager.py
TestQuizzer/quizutils/__init__.py
TestQuizzer/quizutils/quiz.py
TestQuizzer/quizutils/quizparser.py
TestQuizzer-0.0.11.dist-info/LICENSE.txt
TestQuizzer-0.0.11.dist-info/METADATA
TestQuizzer-0.0.11.dist-info/WHEEL
TestQuizzer-0.0.11.dist-info/top_level.txt
TestQuizzer-0.0.11.dist-info/RECORD
